MANIFEST.in
README.rst
setup.py
flake8_diff.egg-info/PKG-INFO
flake8_diff.egg-info/SOURCES.txt
flake8_diff.egg-info/dependency_links.txt
flake8_diff.egg-info/entry_points.txt
flake8_diff.egg-info/not-zip-safe
flake8_diff.egg-info/requires.txt
flake8_diff.egg-info/top_level.txt
flake8diff/__init__.py
flake8diff/__init__.pyc
flake8diff/exceptions.py
flake8diff/exceptions.pyc
flake8diff/flake8.py
flake8diff/flake8.pyc
flake8diff/main.py
flake8diff/main.pyc
flake8diff/test_exceptions.py
flake8diff/test_flake8.py
flake8diff/test_main.py
flake8diff/test_utils.py
flake8diff/utils.py
flake8diff/utils.pyc
flake8diff/vcs/__init__.py
flake8diff/vcs/__init__.pyc
flake8diff/vcs/base.py
flake8diff/vcs/base.pyc
flake8diff/vcs/git.py
flake8diff/vcs/git.pyc
flake8diff/vcs/hg.py
flake8diff/vcs/hg.pyc