Metadata-Version: 1.1
Name: flake8-diff
Version: 0.2.2
Summary: Run flake8 across a set of changed files and filter out violations occurring only on the lines that were changed.
Home-page: http://dealertrack.github.io
Author: Dealertrack Technologies
Author-email: gregory.armer@dealertrack.com
License: UNKNOWN
Download-URL: https://github.com/dealertrack/flake8-diff/releases/tag/v0.2.2
Platform: UNKNOWN
